HISTORY.rst
LICENSE
MANIFEST.in
README.rst
setup.cfg
setup.py
descartes_bi/__init__.py
descartes_bi/urls.py
descartes_bi/wsgi.py
descartes_bi.egg-info/PKG-INFO
descartes_bi.egg-info/SOURCES.txt
descartes_bi.egg-info/dependency_links.txt
descartes_bi.egg-info/not-zip-safe
descartes_bi.egg-info/requires.txt
descartes_bi.egg-info/top_level.txt
descartes_bi/apps/common/__init__.py
descartes_bi/apps/common/models.py
descartes_bi/apps/common/settings.py
descartes_bi/apps/common/urls.py
descartes_bi/apps/common/views.py
descartes_bi/apps/common/locale/es/LC_MESSAGES/django.mo
descartes_bi/apps/common/locale/es/LC_MESSAGES/django.po
descartes_bi/apps/common/management/__init__.py
descartes_bi/apps/common/management/commands/__init__.py
descartes_bi/apps/common/management/commands/initialsetup.py
descartes_bi/apps/common/migrations/0001_initial.py
descartes_bi/apps/common/migrations/0002_auto__add_autoadminsingleton.py
descartes_bi/apps/common/migrations/__init__.py
descartes_bi/apps/common/templatetags/__init__.py
descartes_bi/apps/common/templatetags/autoadmin_tags.py
descartes_bi/apps/common/templatetags/project_tags.py
descartes_bi/apps/core/__init__.py
descartes_bi/apps/core/static/core/images/favicon.ico
descartes_bi/apps/core/static/core/images/favicon.png
descartes_bi/apps/core/static/core/images/logo.png
descartes_bi/apps/core/static/core/images/logo_black.png
descartes_bi/apps/core/static/core/images/backgrounds/minimalistic_violet_purple_blue_artwallpaperhi_com.jpg
descartes_bi/apps/core/static/core/packages/jquery-2.1.1.min.js
descartes_bi/apps/core/static/core/packages/bootstrap-3.2.0-dist/css/bootstrap-theme.css
descartes_bi/apps/core/static/core/packages/bootstrap-3.2.0-dist/css/bootstrap-theme.min.css
descartes_bi/apps/core/static/core/packages/bootstrap-3.2.0-dist/css/bootstrap.css
descartes_bi/apps/core/static/core/packages/bootstrap-3.2.0-dist/css/bootstrap.min.css
descartes_bi/apps/core/static/core/packages/bootstrap-3.2.0-dist/fonts/glyphicons-halflings-regular.eot
descartes_bi/apps/core/static/core/packages/bootstrap-3.2.0-dist/fonts/glyphicons-halflings-regular.svg
