Metadata-Version: 1.1
Name: descartes-bi
Version: 2.0.rc1
Summary: Free Open Source web based business intelligence software.
Home-page: https://github.com/rosarior/descartes_bi
Author: Roberto Rosario
Author-email: roberto.rosario.gonzalez@gmail.com
License:    Copyright 2011 Roberto Rosario
